pygbm/__init__.py
pygbm/binning.py
pygbm/gradient_boosting.py
pygbm/grower.py
pygbm/histogram.py
pygbm/loss.py
pygbm/plotting.py
pygbm/predictor.py
pygbm/splitting.py
pygbm/utils.py
pygbm-0.1.0.dev0.dist-info/LICENSE.txt
pygbm-0.1.0.dev0.dist-info/METADATA
pygbm-0.1.0.dev0.dist-info/WHEEL
pygbm-0.1.0.dev0.dist-info/top_level.txt
pygbm-0.1.0.dev0.dist-info/RECORD
