Metadata-Version: 2.1
Name: pygbm
Version: 0.1.0.dev0
Summary: Experimental, numba-based Gradient Boosting Machines
Home-page: https://github.com/ogrisel/pygbm/
Author: Olivier Grisel
Author-email: olivier.grisel@ensta.org
License: MIT
Platform: any
Classifier: Development Status :: 3 - Alpha
Classifier: Environment :: Console
Classifier: Intended Audience :: Developers
Classifier: Intended Audience :: Science/Research
Classifier: License :: OSI Approved :: MIT License
Classifier: Operating System :: OS Independent
Classifier: Programming Language :: Python :: 3.6
Classifier: Programming Language :: Python :: 3.7
Classifier: Topic :: Scientific/Engineering
Requires-Python: >=3.6
Requires-Dist: numpy
Requires-Dist: scipy
Requires-Dist: scikit-learn
Requires-Dist: numba
